ggufy_cli/__init__.py
ggufy_cli/__main__.py
ggufy-0.1.4.dist-info/METADATA
ggufy-0.1.4.dist-info/WHEEL
ggufy-0.1.4.dist-info/entry_points.txt
ggufy-0.1.4.dist-info/top_level.txt
ggufy-0.1.4.dist-info/RECORD
