Metadata-Version: 2.4
Name: ggufy
Version: 0.1.4
Summary: Python shim that invokes the ggufy binary
Author: nbiish
License: MIT
Project-URL: Homepage, https://github.com/nbiish/ggufy
Project-URL: Repository, https://github.com/nbiish/ggufy
Project-URL: Issues, https://github.com/nbiish/ggufy/issues
Classifier: Programming Language :: Python :: 3
Classifier: Programming Language :: Python :: 3.8
Classifier: Programming Language :: Python :: 3.9
Classifier: Programming Language :: Python :: 3.10
Classifier: Programming Language :: Python :: 3.11
Classifier: Programming Language :: Python :: 3.12
Classifier: License :: OSI Approved :: MIT License
Classifier: Operating System :: OS Independent
Requires-Python: >=3.8
